odoo/addons/mail_preview_base/README.rst
odoo/addons/mail_preview_base/__init__.py
odoo/addons/mail_preview_base/__manifest__.py
odoo/addons/mail_preview_base/i18n/it.po
odoo/addons/mail_preview_base/i18n/mail_preview_base.pot
odoo/addons/mail_preview_base/readme/CONTRIBUTORS.rst
odoo/addons/mail_preview_base/readme/DESCRIPTION.rst
odoo/addons/mail_preview_base/readme/USAGE.rst
odoo/addons/mail_preview_base/static/description/icon.png
odoo/addons/mail_preview_base/static/description/index.html
odoo/addons/mail_preview_base/static/src/js/preview.js
odoo/addons/mail_preview_base/static/src/scss/preview.scss
odoo/addons/mail_preview_base/static/src/xml/preview.xml
odoo/addons/mail_preview_base/template/assets.xml
odoo/addons/mail_preview_base/views/ir_attachment_view.xml
odoo14_addon_mail_preview_base-14.0.1.0.1.dev5.dist-info/METADATA
odoo14_addon_mail_preview_base-14.0.1.0.1.dev5.dist-info/WHEEL
odoo14_addon_mail_preview_base-14.0.1.0.1.dev5.dist-info/top_level.txt
odoo14_addon_mail_preview_base-14.0.1.0.1.dev5.dist-info/RECORD
